{"B08QPPGNNZ":{"productName":"MediChair Kneeling Chair","cogs":{"unitManufacturingCost":888,"shipmentUnitCost":2222,"monthlyAdvertismentCost":33333,"manufacturingCountry":"AS"}},"B093TGGHS7":{"productName":"BESTKID BALL Kids Basketball Size 6","cogs":{"unitManufacturingCost":862,"shipmentUnitCost":242,"monthlyAdvertismentCost":855,"manufacturingCountry":"NG"}},"B078J1F569":{"productName":"Drawing Stencil Set for Kids with 240+ Shapes.","cogs":{"unitManufacturingCost":267,"shipmentUnitCost":335,"monthlyAdvertismentCost":631,"manufacturingCountry":"ID"}},"B07WJFLTX8":{"productName":"Arcade Basketball Hoop Game by BestKidBall","cogs":{"unitManufacturingCost":72,"shipmentUnitCost":944,"monthlyAdvertismentCost":727,"manufacturingCountry":"TR"}},"B07DR11VS2":{"productName":"Bachelorette Party Drinking Straws","cogs":{"unitManufacturingCost":202,"shipmentUnitCost":41,"monthlyAdvertismentCost":306,"manufacturingCountry":"CL"}},"B086SFXDNF":{"productName":"BESTKID BALL Swimming Pool Basketball Hoop","cogs":{"unitManufacturingCost":93,"shipmentUnitCost":632,"monthlyAdvertismentCost":956,"manufacturingCountry":"VU"}},"B093TGTLNQ":{"productName":"BESTKID BALL Holographic Basketball","cogs":{"unitManufacturingCost":282,"shipmentUnitCost":702,"monthlyAdvertismentCost":439,"manufacturingCountry":"PF"}},"B07DR3LS7Y":{"productName":"Bachelorette Party Straws","cogs":{"unitManufacturingCost":663,"shipmentUnitCost":493,"monthlyAdvertismentCost":677,"manufacturingCountry":"NF"}},"B08CVTFH33":{"productName":"BESTKID BALL Indoor Basketball Game","cogs":{"unitManufacturingCost":252,"shipmentUnitCost":851,"monthlyAdvertismentCost":329,"manufacturingCountry":"BW"}}}